{
    "input_dict": {
        "progname": "Ex10",
        "candidate": "(x7 || !x9) && (!x7 || x9)",
        "init_states": "(x7 || !x9) && (!x7 || x9) && (x12 || !x16) && (!x12 || x16)",
        "iterations": 1
    },
    "parameters_dict": {
        "epsilon": 0.05,
        "delta": 0.1,
        "t": 500
    },
    "output_dict": {
        "Sampled output states": [
            4099,
            32772,
            34822,
            43015,
            8198,
            28681,
            43018,
            12,
            51215,
            12307,
            16403,
            59413,
            34839,
            28695,
            32797,
            6174,
            16414,
            2078,
            51233,
            12320,
            8225,
            61471,
            4136,
            36907,
            59437,
            12334,
            61486,
            24629,
            32822,
            56,
            34874,
            55357,
            8255,
            12351,
            34884,
            34886,
            55369,
            63561,
            36943,
            41048,
            41049,
            18522,
            43097,
            14431,
            34916,
            49259,
            6253,
            10350,
            111,
            53360,
            4212,
            63608,
            63610,
            10364,
            8319,
            26757,
            43144,
            43146,
            16523,
            30860,
            16526,
            41103,
            47249,
            18578,
            37011,
            49300,
            53396,
            28826,
            4253,
            49309,
            45216,
            28836,
            24740,
            166,
            2215,
            45232,
            8371,
            57527,
            20665,
            4281,
            2237,
            190,
            6336,
            41155,
            12484,
            24780,
            2255,
            24789,
            61655,
            24793,
            43228,
            16606,
            4320,
            14563,
            8420,
            59620,
            8425,
            49386,
            45290,
            47340,
            53482,
            59630,
            239,
            43247,
            20713,
            242,
            49393,
            63735,
            16638,
            18944,
            23041,
            47616,
            27142,
            39431,
            37386,
            2570,
            33294,
            4624,
            39440,
            25105,
            4627,
            55828,
            27157,
            53781,
            49687,
            61977,
            4634,
            59932,
            25116,
            18976,
            25120,
            57890,
            37411,
            39459,
            2598,
            14897,
            29233,
            4657,
            16945,
            49718,
            55868,
            47677,
            6716,
            4674,
            45635,
            51781,
            29255,
            27210,
            33358,
            16976,
            6737,
            12882,
            27217,
            43601,
            2645,
            2648,
            57956,
            8806,
            31337,
            39530,
            43627,
            12908,
            29294,
            4719,
            27248,
            25199,
            60015,
            41587,
            10872,
            57977,
            10874,
            55931,
            57980,
            17016,
            12927,
            53890,
            53893,
            25222,
            21127,
            19081,
            6794,
            35467,
            47756,
            47758,
            29327,
            6800,
            19091,
            58004,
            27285,
            49814,
            29335,
            29332,
            2714,
            49822,
            15007,
            6816,
            27300,
            29349,
            64168,
            37545,
            51883,
            29371,
            6844,
            53948,
            23231,
            49859,
            47811,
            49861,
            17093,
            53958,
            23240,
            13001,
            53962,
            4807,
            33484,
            62157,
            45774,
            39629,
            53959,
            41683,
            13012,
            15064,
            58073,
            43737,
            10970,
            21215,
            23264,
            33509,
            49899,
            17131,
            15085,
            33518,
            47856,
            43762,
            62195,
            35572,
            54004,
            4861,
            127743,
            123647,
            19713,
            46337,
            23812,
            60680,
            1289,
            62732,
            50447,
            46352,
            60691,
            3348,
            17684,
            36121,
            29982,
            29983,
            5411,
            13604,
            25895,
            54567,
            54570,
            1324,
            34093,
            5420,
            19759,
            27953,
            42297,
            46395,
            17723,
            58683,
            9535,
            30015,
            36159,
            3391,
            42308,
            19780,
            40262,
            36171,
            36176,
            64849,
            34130,
            52566,
            3419,
            50525,
            9570,
            1381,
            3435,
            46444,
            19821,
            15726,
            13683,
            50550,
            56695,
            15741,
            42367,
            54656,
            17793,
            13698,
            25986,
            64901,
            42375,
            54667,
            17804,
            42379,
            7566,
            60816,
            17809,
            5521,
            48533,
            21911,
            58781,
            40349,
            30111,
            19871,
            30115,
            54692,
            30118,
            5544,
            40360,
            52650,
            17836,
            40367,
            21935,
            54705,
            15796,
            13752,
            5560,
            62906,
            56763,
            17854,
            7614,
            26049,
            26050,
            13762,
            17859,
            48581,
            24007,
            26058,
            17866,
            15824,
            48593,
            48592,
            30163,
            9684,
            48597,
            5590,
            28115,
            36307,
            15835,
            24033,
            32226,
            26083,
            24037,
            9702,
            11751,
            64999,
            11752,
            7661,
            62962,
            36341,
            7670,
            32247,
            32246,
            15863,
            30205,
            44541,
            19966,
            42752,
            20225,
            65282,
            57099,
            26380,
            24338,
            32533,
            7959,
            24344,
            48924,
            32543,
            42788,
            59173,
            3878,
            12071,
            18216,
            48937,
            61222,
            46888,
            12079,
            57136,
            46896,
            46898,
            63283,
            7990,
            1847,
            48952,
            36665,
            65339,
            3901,
            34622,
            59203,
            8005,
            22341,
            36679,
            26440,
            53065,
            30537,
            3910,
            53069,
            65359,
            53072,
            8017,
            44881,
            26459,
            5980,
            65373,
            26462,
            26463,
            18271,
            22367,
            59234,
            48996,
            14184,
            44905,
            18286,
            34674,
            61300,
            59256,
            14201,
            61306,
            42873,
            38776,
            49018,
            20352,
            36737,
            42882,
            42880,
            32646,
            12167,
            51087,
            1937,
            59281,
            63380,
            32665,
            57244,
            3997,
            20383,
            1952,
            20389,
            40869,
            38823,
            30632,
            32687,
            44976,
            22450,
            38836,
            10167,
            6074,
            14267,
            53185,
            20420,
            6085,
            47046,
            44997,
            34758,
            24518,
            47048,
            51147,
            14283,
            40909,
            24526,
            51151,
            53202,
            49110,
            30681,
            47069,
            38878,
            14303,
            53215,
            32737,
            4066,
            2019,
            42974,
            22495,
            65510,
            38887,
            8166,
            20454,
            32746,
            22507,
            65507,
            53230,
            53231,
            65518,
            22512,
            47094,
            22521,
            51194
        ],
        "Validifier_value": 0.484,
        "counterexamples": {
            "4099": 0.0020242914979757085,
            "34822": 0.0020242914979757085,
            "39431": 0.0020242914979757085,
            "43015": 0.0020242914979757085,
            "27142": 0.0020242914979757085,
            "37386": 0.0020242914979757085,
            "43018": 0.0020242914979757085,
            "8198": 0.0020242914979757085,
            "2570": 0.0020242914979757085,
            "33294": 0.0020242914979757085,
            "51215": 0.0020242914979757085,
            "12307": 0.0020242914979757085,
            "4627": 0.0020242914979757085,
            "16403": 0.0020242914979757085,
            "34839": 0.0020242914979757085,
            "49687": 0.0020242914979757085,
            "28695": 0.0020242914979757085,
            "4634": 0.0020242914979757085,
            "6174": 0.0020242914979757085,
            "16414": 0.0020242914979757085,
            "18976": 0.0020242914979757085,
            "51233": 0.0020242914979757085,
            "2078": 0.0020242914979757085,
            "12320": 0.0020242914979757085,
            "25120": 0.0020242914979757085,
            "8225": 0.0020242914979757085,
            "61471": 0.0020242914979757085,
            "4136": 0.0020242914979757085,
            "59437": 0.0020242914979757085,
            "14897": 0.0020242914979757085,
            "29233": 0.0020242914979757085,
            "4657": 0.0020242914979757085,
            "16945": 0.0020242914979757085,
            "24629": 0.0020242914979757085,
            "56": 0.0020242914979757085,
            "55868": 0.0020242914979757085,
            "47677": 0.0020242914979757085,
            "55357": 0.0020242914979757085,
            "6716": 0.0020242914979757085,
            "4674": 0.0020242914979757085,
            "45635": 0.0020242914979757085,
            "34886": 0.0020242914979757085,
            "29255": 0.0020242914979757085,
            "27210": 0.0020242914979757085,
            "33358": 0.0020242914979757085,
            "36943": 0.0020242914979757085,
            "12882": 0.0020242914979757085,
            "18522": 0.0020242914979757085,
            "14431": 0.0020242914979757085,
            "57956": 0.0020242914979757085,
            "34916": 0.0020242914979757085,
            "31337": 0.0020242914979757085,
            "12908": 0.0020242914979757085,
            "6253": 0.0020242914979757085,
            "27248": 0.0020242914979757085,
            "53360": 0.0020242914979757085,
            "4212": 0.0020242914979757085,
            "63608": 0.0020242914979757085,
            "10872": 0.0020242914979757085,
            "57977": 0.0020242914979757085,
            "17016": 0.0020242914979757085,
            "57980": 0.0020242914979757085,
            "10364": 0.0020242914979757085,
            "53890": 0.0020242914979757085,
            "25222": 0.0020242914979757085,
            "21127": 0.0020242914979757085,
            "43146": 0.0020242914979757085,
            "6794": 0.0020242914979757085,
            "16523": 0.0020242914979757085,
            "35467": 0.0020242914979757085,
            "47758": 0.0020242914979757085,
            "41103": 0.0020242914979757085,
            "29327": 0.0020242914979757085,
            "16526": 0.0020242914979757085,
            "18578": 0.0020242914979757085,
            "19091": 0.0020242914979757085,
            "37011": 0.0020242914979757085,
            "49814": 0.0020242914979757085,
            "29335": 0.0020242914979757085,
            "2714": 0.0020242914979757085,
            "28826": 0.0020242914979757085,
            "49822": 0.0020242914979757085,
            "15007": 0.0020242914979757085,
            "6816": 0.0020242914979757085,
            "45216": 0.0020242914979757085,
            "27300": 0.0020242914979757085,
            "28836": 0.0020242914979757085,
            "29349": 0.0020242914979757085,
            "24740": 0.0020242914979757085,
            "64168": 0.0020242914979757085,
            "37545": 0.0020242914979757085,
            "45232": 0.0020242914979757085,
            "20665": 0.0020242914979757085,
            "4281": 0.0020242914979757085,
            "6844": 0.0020242914979757085,
            "53948": 0.0020242914979757085,
            "2237": 0.0020242914979757085,
            "49859": 0.0020242914979757085,
            "41155": 0.0020242914979757085,
            "47811": 0.0020242914979757085,
            "53958": 0.0020242914979757085,
            "4807": 0.0020242914979757085,
            "53959": 0.0020242914979757085,
            "53962": 0.0020242914979757085,
            "45774": 0.0020242914979757085,
            "2255": 0.0020242914979757085,
            "41683": 0.0020242914979757085,
            "61655": 0.0020242914979757085,
            "10970": 0.0020242914979757085,
            "16606": 0.0020242914979757085,
            "21215": 0.0020242914979757085,
            "4320": 0.0020242914979757085,
            "23264": 0.0020242914979757085,
            "8420": 0.0020242914979757085,
            "33509": 0.0020242914979757085,
            "59620": 0.0020242914979757085,
            "8425": 0.0020242914979757085,
            "20713": 0.0020242914979757085,
            "47340": 0.0020242914979757085,
            "15085": 0.0020242914979757085,
            "47856": 0.0020242914979757085,
            "49393": 0.0020242914979757085,
            "35572": 0.0020242914979757085,
            "54004": 0.0020242914979757085,
            "4861": 0.0020242914979757085,
            "65282": 0.0020242914979757085,
            "57099": 0.0020242914979757085,
            "50447": 0.0020242914979757085,
            "24338": 0.0020242914979757085,
            "60691": 0.0020242914979757085,
            "7959": 0.0020242914979757085,
            "29982": 0.0020242914979757085,
            "32543": 0.0020242914979757085,
            "29983": 0.0020242914979757085,
            "42788": 0.0020242914979757085,
            "59173": 0.0020242914979757085,
            "13604": 0.0020242914979757085,
            "18216": 0.0020242914979757085,
            "48937": 0.0020242914979757085,
            "46888": 0.0020242914979757085,
            "1324": 0.0020242914979757085,
            "34093": 0.0020242914979757085,
            "5420": 0.0020242914979757085,
            "57136": 0.0020242914979757085,
            "46896": 0.0020242914979757085,
            "27953": 0.0020242914979757085,
            "48952": 0.0020242914979757085,
            "36665": 0.0020242914979757085,
            "42297": 0.0020242914979757085,
            "3901": 0.0020242914979757085,
            "59203": 0.0020242914979757085,
            "3910": 0.0020242914979757085,
            "36679": 0.0020242914979757085,
            "40262": 0.0020242914979757085,
            "36171": 0.0020242914979757085,
            "65359": 0.0020242914979757085,
            "34130": 0.0020242914979757085,
            "52566": 0.0020242914979757085,
            "26459": 0.0020242914979757085,
            "3419": 0.0020242914979757085,
            "26462": 0.0020242914979757085,
            "26463": 0.0020242914979757085,
            "18271": 0.0020242914979757085,
            "44541": 0.0020242914979757085,
            "22367": 0.0020242914979757085,
            "48996": 0.0020242914979757085,
            "1381": 0.0020242914979757085,
            "14184": 0.0020242914979757085,
            "44905": 0.0020242914979757085,
            "46444": 0.0020242914979757085,
            "19821": 0.0020242914979757085,
            "61300": 0.0020242914979757085,
            "59256": 0.0020242914979757085,
            "14201": 0.0020242914979757085,
            "42873": 0.0020242914979757085,
            "38776": 0.0020242914979757085,
            "15741": 0.0020242914979757085,
            "13698": 0.0020242914979757085,
            "42882": 0.0020242914979757085,
            "25986": 0.0020242914979757085,
            "32646": 0.0020242914979757085,
            "42375": 0.0020242914979757085,
            "12167": 0.0020242914979757085,
            "54667": 0.0020242914979757085,
            "42379": 0.0020242914979757085,
            "7566": 0.0020242914979757085,
            "51087": 0.0020242914979757085,
            "21911": 0.0020242914979757085,
            "20383": 0.0020242914979757085,
            "1952": 0.0020242914979757085,
            "30111": 0.0020242914979757085,
            "19871": 0.0020242914979757085,
            "54692": 0.0020242914979757085,
            "20389": 0.0020242914979757085,
            "40869": 0.0020242914979757085,
            "5544": 0.0020242914979757085,
            "30632": 0.0020242914979757085,
            "40360": 0.0020242914979757085,
            "17836": 0.0020242914979757085,
            "44976": 0.0020242914979757085,
            "54705": 0.0020242914979757085,
            "15796": 0.0020242914979757085,
            "38836": 0.0020242914979757085,
            "13752": 0.0020242914979757085,
            "5560": 0.0020242914979757085,
            "26050": 0.0020242914979757085,
            "13762": 0.0020242914979757085,
            "17859": 0.0020242914979757085,
            "47046": 0.0020242914979757085,
            "24007": 0.0020242914979757085,
            "34758": 0.0020242914979757085,
            "24518": 0.0020242914979757085,
            "26058": 0.0020242914979757085,
            "51147": 0.0020242914979757085,
            "14283": 0.0020242914979757085,
            "17866": 0.0020242914979757085,
            "24526": 0.0020242914979757085,
            "51151": 0.0020242914979757085,
            "53202": 0.0020242914979757085,
            "30163": 0.0020242914979757085,
            "28115": 0.0020242914979757085,
            "36307": 0.0020242914979757085,
            "5590": 0.0020242914979757085,
            "49110": 0.0020242914979757085,
            "15835": 0.0020242914979757085,
            "38878": 0.0020242914979757085,
            "14303": 0.0020242914979757085,
            "53215": 0.0020242914979757085,
            "32737": 0.0020242914979757085,
            "24033": 0.0020242914979757085,
            "42974": 0.0020242914979757085,
            "22495": 0.0020242914979757085,
            "24037": 0.0020242914979757085,
            "11752": 0.0020242914979757085,
            "7661": 0.0020242914979757085,
            "22512": 0.0020242914979757085,
            "36341": 0.0020242914979757085,
            "22521": 0.0020242914979757085,
            "30205": 0.0020242914979757085
        }
    }
}