{
    "input_dict": {
        "progname": "Ex7",
        "candidate": "(!x7 && !x1 && !x4 && !x6 && !x10) || (!x7 && !x1 && !x4 && x6 && x10) || (!x7 && !x1 && x4 && !x8) || (!x7 && !x1 && x4 && x8 && !x6 && !x10) || (!x7 && !x1 && x4 && x8 && x6 && x10) || (x7 && x1 && !x2 && !x4 && !x8 && !x9) || (x7 && x1 && !x2 && !x4 && !x8 && x9 && !x5 && x10 && x6) || (x7 && x1 && !x2 && !x4 && !x8 && x9 && x5) || (x7 && x1 && !x2 && !x4 && x8 && !x5) || (x7 && x1 && !x2 && !x4 && x8 && x5 && x6 && !x3) || (x7 && x1 && !x2 && x4 && !x10) || (x7 && x1 && !x2 && x4 && x10 && x6) || (x7 && x1 && x2 && !x3 && !x8) || (x7 && x1 && x2 && !x3 && x8 && !x5 && !x6) || (x7 && x1 && x2 && !x3 && x8 && !x5 && x6 && x10) || (x7 && x1 && x2 && !x3 && x8 && x5 && x4 && x9) || (x7 && x1 && x2 && x3 && !x8 && x4 && !x9 && x10 && x6) || (x7 && x1 && x2 && x3 && !x8 && x4 && x9) || (x7 && x1 && x2 && x3 && x8 && !x5 && !x4) || (x7 && x1 && x2 && x3 && x8 && x5)",
        "init_states": "(x1 || !x7) && (!x1 || x7) && (x6 || !x10) && (!x6 || x10)",
        "iterations": 1
    },
    "parameters_dict": {
        "epsilon": 0.05,
        "delta": 0.1,
        "t": 1
    },
    "output_dict": {
        "Sampled output states": [
            92
        ],
        "Validifier_value": 0.0,
        "counterexamples": {}
    }
}