{
    "input_dict": {
        "progname": "Ex9",
        "candidate": "(x1 || !x2) && (!x1 || x2)",
        "init_states": "(x1 || !x2) && (!x1 || x2) && (x3 || !x4) && (!x3 || x4)",
        "iterations": 1
    },
    "parameters_dict": {
        "epsilon": 0.05,
        "delta": 0.1,
        "m1": 600,
        "m2": 10
    },
    "output_dict": {
        "Reachability_dict": {
            "65598": 51,
            "122942": 38,
            "126846": 25,
            "68345": 16,
            "69369": 5,
            "68478": 7,
            "126713": 1,
            "69502": 54,
            "125502": 19,
            "76350": 16,
            "99710": 81,
            "50558": 25,
            "49534": 7,
            "107814": 44,
            "107942": 2,
            "50470": 10,
            "51582": 7,
            "108670": 24,
            "109950": 27,
            "52606": 30,
            "108926": 8,
            "51326": 39,
            "109070": 29,
            "100878": 64,
            "68222": 50,
            "53118": 29,
            "52094": 11,
            "102270": 57,
            "101246": 13,
            "102137": 5,
            "101113": 14,
            "51838": 21,
            "52862": 2,
            "102014": 5,
            "98318": 24,
            "49166": 22,
            "116862": 35,
            "116985": 7,
            "67710": 64,
            "109614": 2,
            "109870": 13,
            "108862": 4,
            "52270": 2,
            "51518": 3,
            "116798": 5,
            "52526": 10,
            "99622": 32,
            "124166": 47,
            "66822": 32,
            "102150": 35,
            "52742": 4,
            "51726": 15,
            "52998": 7,
            "117374": 21,
            "118654": 27,
            "126590": 4,
            "125822": 4,
            "69246": 4,
            "125566": 36,
            "117630": 7,
            "101000": 3,
            "49214": 24,
            "98366": 54,
            "49342": 4,
            "100478": 66,
            "98958": 13,
            "98830": 29,
            "101758": 47,
            "101502": 4,
            "125054": 45,
            "67833": 15,
            "125177": 11,
            "109760": 2,
            "118142": 14,
            "109894": 13,
            "52473": 4,
            "118009": 3,
            "49726": 12,
            "107070": 16,
            "77102": 18,
            "75961": 1,
            "76968": 1,
            "125113": 3,
            "124942": 42,
            "125070": 1,
            "67726": 4,
            "67598": 34,
            "114702": 15,
            "65550": 40,
            "115974": 32,
            "114958": 6,
            "100134": 43,
            "99134": 10,
            "108326": 13,
            "108450": 2,
            "100258": 1,
            "116486": 19,
            "67334": 23,
            "66318": 4,
            "126254": 19,
            "68910": 15,
            "67902": 8,
            "126120": 1,
            "107022": 23,
            "116094": 29,
            "116217": 5,
            "66942": 46,
            "65785": 8,
            "116134": 2,
            "65726": 4,
            "114878": 1,
            "116006": 16,
            "66854": 23,
            "75790": 24,
            "125064": 3,
            "75912": 10,
            "100734": 7,
            "107902": 30,
            "108025": 2,
            "98553": 7,
            "98686": 9,
            "124286": 21,
            "67065": 3,
            "117262": 18,
            "68110": 28,
            "125518": 8,
            "117118": 8,
            "68990": 64,
            "117894": 2,
            "67854": 8,
            "118022": 23,
            "116878": 2,
            "68870": 32,
            "124798": 38,
            "67454": 49,
            "67577": 6,
            "106510": 51,
            "66430": 13,
            "124742": 16,
            "108558": 24,
            "116750": 25,
            "51214": 16,
            "101625": 9,
            "100601": 15,
            "109574": 3,
            "100366": 40,
            "100622": 10,
            "109830": 29,
            "108814": 10,
            "106681": 2,
            "106558": 23,
            "49337": 3,
            "68158": 27,
            "117310": 20,
            "99198": 11,
            "51070": 30,
            "100222": 91,
            "100990": 74,
            "98430": 88,
            "117390": 2,
            "124678": 38,
            "124800": 1,
            "67456": 1,
            "117006": 3,
            "118062": 6,
            "68776": 1,
            "117054": 2,
            "117928": 2,
            "116872": 2,
            "67720": 3,
            "74302": 7,
            "123454": 14,
            "67646": 25,
            "124990": 32,
            "98942": 84,
            "107086": 28,
            "99065": 26,
            "50046": 3,
            "67769": 6,
            "49678": 8,
            "65662": 45,
            "123006": 42,
            "123129": 3,
            "98440": 2,
            "49288": 3,
            "108622": 44,
            "51449": 8,
            "108744": 12,
            "101638": 37,
            "109696": 6,
            "101504": 6,
            "101382": 6,
            "108686": 1,
            "52486": 13,
            "52358": 1,
            "108294": 33,
            "50950": 2,
            "49934": 3,
            "107134": 23,
            "49790": 43,
            "107257": 4,
            "107144": 3,
            "110342": 22,
            "110086": 2,
            "109326": 6,
            "98622": 6,
            "99833": 2,
            "101894": 7,
            "101134": 6,
            "65918": 6,
            "114814": 26,
            "77318": 1,
            "125710": 10,
            "126726": 30,
            "76558": 3,
            "77574": 11,
            "124921": 6,
            "76424": 4,
            "76302": 8,
            "125454": 14,
            "109192": 4,
            "49806": 2,
            "108422": 4,
            "101006": 6,
            "98494": 1,
            "75838": 22,
            "76846": 1,
            "107846": 23,
            "107968": 2,
            "49401": 7,
            "50681": 3,
            "98489": 3,
            "125006": 33,
            "125128": 5,
            "73854": 13,
            "66174": 29,
            "123592": 1,
            "66297": 9,
            "123470": 14,
            "100488": 10,
            "69382": 26,
            "126470": 1,
            "101422": 4,
            "101678": 15,
            "115262": 24,
            "66110": 37,
            "98878": 52,
            "99001": 9,
            "126278": 23,
            "125262": 9,
            "68734": 2,
            "100926": 30,
            "123065": 3,
            "65721": 4,
            "125640": 4,
            "126334": 40,
            "67966": 11,
            "125310": 7,
            "100542": 3,
            "101550": 4,
            "108734": 1,
            "100670": 5,
            "109742": 1,
            "109694": 2,
            "106574": 39,
            "49278": 29,
            "115326": 8,
            "99590": 33,
            "69422": 26,
            "126766": 20,
            "69166": 7,
            "68414": 7,
            "115582": 6,
            "116606": 15,
            "65806": 10,
            "68238": 1,
            "117766": 5,
            "66238": 9,
            "123582": 1,
            "117886": 1,
            "108414": 33,
            "76414": 9,
            "117438": 3,
            "118574": 15,
            "68286": 9,
            "117566": 3,
            "110214": 3,
            "126078": 3,
            "68366": 8,
            "69254": 1,
            "100262": 3,
            "50982": 9,
            "99006": 7,
            "73806": 12,
            "122958": 12,
            "124288": 1,
            "75014": 8,
            "75136": 1,
            "107782": 40,
            "98574": 7,
            "110462": 6,
            "65678": 3,
            "66950": 3,
            "123406": 12,
            "66062": 24,
            "118398": 5,
            "102062": 6,
            "102190": 26,
            "114750": 17,
            "118534": 8,
            "118278": 1,
            "67774": 9,
            "125118": 4,
            "67462": 1,
            "73918": 3,
            "73790": 14,
            "108793": 3,
            "100102": 22,
            "99086": 8,
            "124864": 3,
            "106745": 6,
            "106622": 23,
            "114824": 3,
            "100230": 2,
            "123518": 26,
            "101510": 2,
            "109198": 3,
            "51961": 8,
            "115214": 28,
            "77126": 10,
            "76870": 3,
            "75854": 13,
            "76110": 2,
            "122894": 34,
            "123016": 9,
            "65672": 7,
            "100345": 6,
            "68782": 2,
            "73742": 17,
            "123022": 3,
            "73870": 2,
            "126790": 9,
            "76473": 3,
            "125625": 8,
            "68857": 6,
            "124409": 3,
            "124230": 15,
            "75078": 18,
            "75200": 5,
            "123070": 1,
            "49800": 3,
            "98952": 2,
            "100414": 32,
            "100537": 4,
            "108729": 8,
            "108606": 21,
            "53038": 5,
            "51193": 1,
            "115006": 1,
            "66978": 1,
            "116130": 3,
            "124710": 20,
            "75558": 15,
            "75686": 2,
            "108358": 12,
            "75966": 2,
            "76094": 1,
            "125246": 1,
            "126598": 1,
            "117497": 6,
            "49913": 7,
            "107208": 5,
            "108480": 3,
            "51342": 2,
            "100494": 7,
            "75526": 10,
            "126201": 4,
            "51262": 6,
            "108537": 3,
            "123641": 3,
            "49854": 2,
            "108454": 9,
            "126214": 19,
            "125198": 4,
            "125958": 4,
            "68654": 1,
            "51774": 12,
            "50438": 19,
            "49422": 4,
            "125689": 4,
            "115336": 3,
            "66184": 5,
            "125758": 2,
            "51470": 1,
            "51078": 1,
            "124326": 2,
            "124198": 18,
            "108416": 1,
            "109374": 2,
            "52030": 1,
            "109241": 2,
            "51897": 2,
            "110382": 12,
            "106696": 4,
            "109390": 2,
            "110272": 3,
            "110406": 6,
            "118446": 1,
            "114830": 3,
            "74366": 12,
            "65854": 4,
            "66982": 2,
            "126656": 2,
            "118521": 1,
            "101054": 4,
            "101182": 5,
            "68232": 3,
            "125576": 3,
            "50566": 4,
            "116729": 2,
            "77182": 4,
            "77049": 1,
            "107938": 1,
            "49470": 1,
            "49294": 2,
            "106638": 1,
            "114873": 1,
            "126592": 2,
            "77440": 1,
            "75590": 9,
            "115390": 2,
            "116926": 3,
            "115342": 2,
            "66190": 5,
            "124294": 5,
            "52864": 2,
            "126144": 2,
            "109246": 2,
            "109118": 12,
            "68281": 3,
            "117433": 3,
            "67366": 4,
            "116518": 4,
            "115518": 1,
            "67494": 1,
            "117384": 3,
            "117518": 1,
            "99718": 3,
            "75646": 13,
            "115070": 5,
            "114937": 3,
            "108878": 2,
            "74318": 14,
            "74440": 1,
            "77638": 2,
            "77504": 1,
            "76488": 4,
            "76622": 1,
            "107910": 1,
            "116096": 1,
            "75902": 6,
            "109182": 4,
            "109305": 2,
            "75976": 5,
            "52985": 1,
            "125998": 1,
            "126086": 2,
            "107193": 1,
            "76537": 3,
            "107904": 2,
            "76366": 5,
            "125630": 4,
            "69294": 1,
            "116608": 1,
            "124352": 2,
            "126080": 2,
            "77062": 5,
            "76046": 1,
            "76928": 1,
            "52350": 1,
            "68736": 1,
            "51982": 1,
            "110126": 2,
            "68742": 1,
            "69248": 2,
            "125774": 1,
            "123080": 1,
            "109134": 3,
            "109256": 1,
            "124322": 1,
            "75769": 2,
            "115449": 2,
            "108680": 3,
            "101049": 4,
            "77486": 1,
            "76606": 3,
            "77614": 2,
            "124806": 4,
            "77561": 1,
            "77694": 6
        },
        "DistEstimate_value": 0.12483333333333335,
        "counterexamples": {
            "69369": 0.0008333333333333334,
            "68478": 0.0011666666666666668,
            "126713": 0.00016666666666666666,
            "108926": 0.0013333333333333333,
            "53118": 0.004833333333333334,
            "52094": 0.0018333333333333333,
            "101246": 0.0021666666666666666,
            "102137": 0.0008333333333333334,
            "51838": 0.0035,
            "52862": 0.0003333333333333333,
            "102014": 0.0008333333333333334,
            "109614": 0.0003333333333333333,
            "108862": 0.0006666666666666666,
            "52742": 0.0006666666666666666,
            "51726": 0.0025,
            "52998": 0.0011666666666666668,
            "126590": 0.0006666666666666666,
            "125822": 0.0006666666666666666,
            "69246": 0.0006666666666666666,
            "117630": 0.0011666666666666668,
            "49342": 0.0006666666666666666,
            "101502": 0.0006666666666666666,
            "109760": 0.0003333333333333333,
            "52473": 0.0006666666666666666,
            "118009": 0.0005,
            "49726": 0.002,
            "76968": 0.00016666666666666666,
            "114958": 0.001,
            "99134": 0.0016666666666666668,
            "66318": 0.0006666666666666666,
            "67902": 0.0013333333333333333,
            "126120": 0.00016666666666666666,
            "100734": 0.0011666666666666668,
            "98686": 0.0015,
            "117118": 0.0013333333333333333,
            "117894": 0.0003333333333333333,
            "67854": 0.0013333333333333333,
            "66430": 0.0021666666666666666,
            "101625": 0.0015,
            "109574": 0.0005,
            "100622": 0.0016666666666666668,
            "108814": 0.0016666666666666668,
            "49337": 0.0005,
            "99198": 0.0018333333333333333,
            "51070": 0.005,
            "117006": 0.0005,
            "68776": 0.00016666666666666666,
            "117054": 0.0003333333333333333,
            "117928": 0.0003333333333333333,
            "50046": 0.0005,
            "49678": 0.0013333333333333333,
            "49288": 0.0005,
            "51449": 0.0013333333333333333,
            "109696": 0.001,
            "101504": 0.001,
            "101382": 0.001,
            "52358": 0.00016666666666666666,
            "50950": 0.0003333333333333333,
            "49934": 0.0005,
            "49790": 0.007166666666666667,
            "110086": 0.0003333333333333333,
            "109326": 0.001,
            "98622": 0.001,
            "101894": 0.0011666666666666668,
            "101134": 0.001,
            "65918": 0.001,
            "77318": 0.00016666666666666666,
            "125710": 0.0016666666666666668,
            "76558": 0.0005,
            "76846": 0.00016666666666666666,
            "49401": 0.0011666666666666668,
            "50681": 0.0005,
            "126470": 0.00016666666666666666,
            "101422": 0.0006666666666666666,
            "125262": 0.0015,
            "68734": 0.0003333333333333333,
            "67966": 0.0018333333333333333,
            "125310": 0.0011666666666666668,
            "101550": 0.0006666666666666666,
            "100670": 0.0008333333333333334,
            "109742": 0.00016666666666666666,
            "109694": 0.0003333333333333333,
            "69166": 0.0011666666666666668,
            "68414": 0.0011666666666666668,
            "115582": 0.001,
            "65806": 0.0016666666666666668,
            "117766": 0.0008333333333333334,
            "117886": 0.00016666666666666666,
            "117566": 0.0005,
            "110214": 0.0005,
            "126078": 0.0005,
            "68366": 0.0013333333333333333,
            "69254": 0.00016666666666666666,
            "50982": 0.0015,
            "98574": 0.0011666666666666668,
            "118398": 0.0008333333333333334,
            "102062": 0.001,
            "118278": 0.00016666666666666666,
            "99086": 0.0013333333333333333,
            "101510": 0.0003333333333333333,
            "76870": 0.0005,
            "76110": 0.0003333333333333333,
            "68782": 0.0003333333333333333,
            "68857": 0.001,
            "53038": 0.0008333333333333334,
            "115006": 0.00016666666666666666,
            "76094": 0.00016666666666666666,
            "125246": 0.00016666666666666666,
            "126598": 0.00016666666666666666,
            "51342": 0.0003333333333333333,
            "126201": 0.0006666666666666666,
            "125198": 0.0006666666666666666,
            "125958": 0.0006666666666666666,
            "68654": 0.00016666666666666666,
            "51774": 0.002,
            "125758": 0.0003333333333333333,
            "109374": 0.0003333333333333333,
            "52030": 0.00016666666666666666,
            "109390": 0.0003333333333333333,
            "110272": 0.0005,
            "118446": 0.00016666666666666666,
            "65854": 0.0006666666666666666,
            "126656": 0.0003333333333333333,
            "118521": 0.00016666666666666666,
            "101182": 0.0008333333333333334,
            "50566": 0.0006666666666666666,
            "77049": 0.00016666666666666666,
            "49294": 0.0003333333333333333,
            "126592": 0.0003333333333333333,
            "77440": 0.00016666666666666666,
            "126144": 0.0003333333333333333,
            "115518": 0.00016666666666666666,
            "117518": 0.00016666666666666666,
            "115070": 0.0008333333333333334,
            "108878": 0.0003333333333333333,
            "77504": 0.00016666666666666666,
            "76622": 0.00016666666666666666,
            "125998": 0.00016666666666666666,
            "126086": 0.0003333333333333333,
            "69294": 0.00016666666666666666,
            "126080": 0.0003333333333333333,
            "76046": 0.00016666666666666666,
            "76928": 0.00016666666666666666,
            "68736": 0.00016666666666666666,
            "51982": 0.00016666666666666666,
            "110126": 0.0003333333333333333,
            "68742": 0.00016666666666666666,
            "69248": 0.0003333333333333333,
            "125774": 0.00016666666666666666,
            "77486": 0.00016666666666666666,
            "76606": 0.0005,
            "77561": 0.00016666666666666666
        }
    }
}