{
    "input_dict": {
        "progname": "Ex11",
        "candidate": "(!x1 || !x2) && (!x1 || x2 || !x3 || !x6) && (!x1 || x2 || !x3 || x6 || !x7) && (!x1 || x2 || !x3 || x6 || x7 || x8) && (!x1 || x2 || x3 || !x4 || x6 || x7) && (!x1 || x2 || x3 || x4 || !x6) && (!x1 || x2 || x3 || x4 || x6 || !x7) && (!x1 || x2 || x3 || x4 || x6 || x7 || x8) && (x1 || !x2) && (x1 || x2 || !x3 || !x4 || x6 || x7) && (x1 || x2 || !x3 || x4 || !x6) && (x1 || x2 || !x3 || x4 || x6 || !x7) && (x1 || x2 || !x3 || x4 || x6 || x7 || x8) && (x1 || x2 || x3 || !x6) && (x1 || x2 || x3 || x6 || !x7) && (x1 || x2 || x3 || x6 || x7 || x8)",
        "init_states": "(x1 || !x3) && (!x1 || x3) && (x6 || !x8) && (!x6 || x8)",
        "iterations": 5
    },
    "parameters_dict": {
        "epsilon": 0.05,
        "delta": 0.1,
        "m1": 600,
        "m2": 10
    },
    "output_dict": {
        "Reachability_dict": {
            "49": 214,
            "115": 318,
            "147": 403,
            "151": 390,
            "55": 52,
            "63": 2444,
            "183": 4493,
            "35": 164,
            "131": 1187,
            "0": 660,
            "64": 1373,
            "80": 5394,
            "37": 1884,
            "101": 3375,
            "127": 2261,
            "113": 359,
            "163": 17,
            "135": 311,
            "167": 215,
            "211": 211,
            "133": 662,
            "229": 618,
            "247": 438,
            "245": 159,
            "125": 147,
            "16": 453,
            "19": 130,
            "33": 202,
            "197": 66,
            "195": 112,
            "39": 211,
            "215": 438,
            "213": 147,
            "165": 254,
            "3": 159,
            "97": 79
        },
        "DistEstimate_value": 0.8836333333333334,
        "counterexamples": {
            "49": 0.035666666666666666,
            "115": 0.053,
            "183": 0.7488333333333334,
            "35": 0.027333333333333334,
            "131": 0.19783333333333333,
            "0": 0.11,
            "64": 0.22883333333333333,
            "80": 0.899,
            "37": 0.314,
            "101": 0.5625,
            "127": 0.37683333333333335,
            "113": 0.059833333333333336,
            "163": 0.0028333333333333335,
            "135": 0.051833333333333335,
            "167": 0.035833333333333335,
            "211": 0.035166666666666666,
            "133": 0.11033333333333334,
            "229": 0.103,
            "247": 0.073,
            "245": 0.0265,
            "125": 0.0245,
            "16": 0.0755,
            "19": 0.021666666666666667,
            "197": 0.011,
            "195": 0.018666666666666668,
            "39": 0.035166666666666666,
            "215": 0.073,
            "213": 0.0245,
            "165": 0.042333333333333334,
            "3": 0.0265,
            "97": 0.013166666666666667
        }
    }
}