{
    "input_dict": {
        "progname": "Ex7",
        "candidate": "(!x7 && !x1 && !x4 && !x6 && !x10) || (!x7 && !x1 && !x4 && x6 && x10) || (!x7 && !x1 && x4 && !x8) || (!x7 && !x1 && x4 && x8 && !x6 && !x10) || (!x7 && !x1 && x4 && x8 && x6 && x10) || (x7 && x1 && !x2 && !x4 && !x8 && !x9) || (x7 && x1 && !x2 && !x4 && !x8 && x9 && !x5 && x10 && x6) || (x7 && x1 && !x2 && !x4 && !x8 && x9 && x5) || (x7 && x1 && !x2 && !x4 && x8 && !x5) || (x7 && x1 && !x2 && !x4 && x8 && x5 && x6 && !x3) || (x7 && x1 && !x2 && x4 && !x10) || (x7 && x1 && !x2 && x4 && x10 && x6) || (x7 && x1 && x2 && !x3 && !x8) || (x7 && x1 && x2 && !x3 && x8 && !x5 && !x6) || (x7 && x1 && x2 && !x3 && x8 && !x5 && x6 && x10) || (x7 && x1 && x2 && !x3 && x8 && x5 && x4 && x9) || (x7 && x1 && x2 && x3 && !x8 && x4 && !x9 && x10 && x6) || (x7 && x1 && x2 && x3 && !x8 && x4 && x9) || (x7 && x1 && x2 && x3 && x8 && !x5 && !x4) || (x7 && x1 && x2 && x3 && x8 && x5)",
        "init_states": "(x1 || !x7) && (!x1 || x7) && (x6 || !x10) && (!x6 || x10)",
        "iterations": 1
    },
    "parameters_dict": {
        "epsilon": 0.05,
        "delta": 0.1,
        "m1": 600,
        "m2": 10
    },
    "output_dict": {
        "Reachability_dict": {
            "551": 220,
            "583": 153,
            "839": 91,
            "804": 400,
            "548": 1552,
            "580": 1118,
            "836": 684,
            "807": 61,
            "951": 6,
            "1020": 52,
            "91": 135,
            "88": 514,
            "52": 468,
            "92": 60,
            "576": 50,
            "800": 8,
            "220": 3,
            "544": 40,
            "763": 34,
            "832": 32,
            "48": 44,
            "948": 32,
            "760": 58,
            "1023": 25,
            "55": 106,
            "216": 16,
            "219": 10,
            "308": 1,
            "764": 9,
            "348": 2,
            "1017": 8,
            "311": 4,
            "944": 4
        },
        "DistEstimate_value": 0.9506666666666667,
        "counterexamples": {
            "551": 0.03666666666666667,
            "583": 0.0255,
            "839": 0.015166666666666667,
            "804": 0.06666666666666667,
            "548": 0.25866666666666666,
            "580": 0.18633333333333332,
            "836": 0.114,
            "807": 0.010166666666666666,
            "951": 0.001,
            "91": 0.0225,
            "88": 0.08566666666666667,
            "52": 0.078,
            "92": 0.01,
            "576": 0.008333333333333333,
            "800": 0.0013333333333333333,
            "220": 0.0005,
            "544": 0.006666666666666667,
            "832": 0.005333333333333333,
            "48": 0.007333333333333333,
            "948": 0.005333333333333333,
            "216": 0.0026666666666666666,
            "219": 0.0016666666666666668,
            "308": 0.00016666666666666666,
            "348": 0.0003333333333333333,
            "944": 0.0006666666666666666
        }
    }
}